ovn_bgp_agent/__init__.py
ovn_bgp_agent/agent.py
ovn_bgp_agent/config.py
ovn_bgp_agent/constants.py
ovn_bgp_agent/exceptions.py
ovn_bgp_agent/cmd/__init__.py
ovn_bgp_agent/cmd/agent.py
ovn_bgp_agent/drivers/__init__.py
ovn_bgp_agent/drivers/driver_api.py
ovn_bgp_agent/drivers/openstack/__init__.py
ovn_bgp_agent/drivers/openstack/nb_exceptions.py
ovn_bgp_agent/drivers/openstack/nb_ovn_bgp_driver.py
ovn_bgp_agent/drivers/openstack/ovn_bgp_driver.py
ovn_bgp_agent/drivers/openstack/ovn_evpn_driver.py
ovn_bgp_agent/drivers/openstack/ovn_stretched_l2_bgp_driver.py
ovn_bgp_agent/drivers/openstack/utils/__init__.py
ovn_bgp_agent/drivers/openstack/utils/bgp.py
ovn_bgp_agent/drivers/openstack/utils/common.py
ovn_bgp_agent/drivers/openstack/utils/driver_utils.py
ovn_bgp_agent/drivers/openstack/utils/evpn.py
ovn_bgp_agent/drivers/openstack/utils/frr.py
ovn_bgp_agent/drivers/openstack/utils/loadbalancer.py
ovn_bgp_agent/drivers/openstack/utils/nat.py
ovn_bgp_agent/drivers/openstack/utils/ovn.py
ovn_bgp_agent/drivers/openstack/utils/ovs.py
ovn_bgp_agent/drivers/openstack/utils/port.py
ovn_bgp_agent/drivers/openstack/utils/router.py
ovn_bgp_agent/drivers/openstack/utils/wire.py
ovn_bgp_agent/drivers/openstack/watchers/__init__.py
ovn_bgp_agent/drivers/openstack/watchers/base_watcher.py
ovn_bgp_agent/drivers/openstack/watchers/bgp_watcher.py
ovn_bgp_agent/drivers/openstack/watchers/evpn_watcher.py
ovn_bgp_agent/drivers/openstack/watchers/nb_bgp_watcher.py
ovn_bgp_agent/privileged/__init__.py
ovn_bgp_agent/privileged/linux_net.py
ovn_bgp_agent/privileged/ovs_vsctl.py
ovn_bgp_agent/privileged/vtysh.py
ovn_bgp_agent/tests/__init__.py
ovn_bgp_agent/tests/base.py
ovn_bgp_agent/tests/utils.py
ovn_bgp_agent/tests/functional/__init__.py
ovn_bgp_agent/tests/functional/base.py
ovn_bgp_agent/tests/functional/fixtures.py
ovn_bgp_agent/tests/functional/drivers/__init__.py
ovn_bgp_agent/tests/functional/drivers/openstack/__init__.py
ovn_bgp_agent-5.0.0.dist-info/AUTHORS
ovn_bgp_agent-5.0.0.dist-info/LICENSE
ovn_bgp_agent-5.0.0.dist-info/METADATA
ovn_bgp_agent-5.0.0.dist-info/WHEEL
ovn_bgp_agent-5.0.0.dist-info/entry_points.txt
ovn_bgp_agent-5.0.0.dist-info/pbr.json
ovn_bgp_agent-5.0.0.dist-info/top_level.txt
ovn_bgp_agent-5.0.0.dist-info/RECORD
